order_book.cpython-311-x86_64-linux-gnu.so
order_book-0.6.1.dist-info/LICENSE
order_book-0.6.1.dist-info/METADATA
order_book-0.6.1.dist-info/WHEEL
order_book-0.6.1.dist-info/RECORD
order_book-0.6.1.dist-info/top_level.txt
