Metadata-Version: 2.1
Name: order-book
Version: 0.6.1
Summary: A fast orderbook implementation, in C, for Python
Home-page: https://github.com/bmoscon/orderbook
Author: Bryant Moscon
Author-email: bmoscon@gmail.com
License: License :: OSI Approved :: GNU General Public License v3 (GPLv3)
Keywords: market data,trading
Classifier: Intended Audience :: Developers
Classifier: Development Status :: 3 - Alpha
Classifier: Programming Language :: C
Classifier: Programming Language :: Python
Classifier: Programming Language :: Python :: 3.9
Classifier: Programming Language :: Python :: 3.10
Classifier: Programming Language :: Python :: 3.11
Classifier: Programming Language :: Python :: 3.12
Classifier: Programming Language :: Python :: 3 :: Only
Classifier: Programming Language :: Python :: Implementation :: CPython
Classifier: Operating System :: MacOS
Classifier: Operating System :: POSIX :: Linux
Classifier: Operating System :: POSIX
License-File: LICENSE
